[{"kind": "plus#activity", "provider": {"title": "Reshared Post"}, "title": "+Milky Way\u00a0Over Piton de l'Eau\n\nSometimes, if you wait long enough for a clear and moonless night, the...", "url": "https://plus.google.com/106186407539128840569/posts/62u8QZhfG4U", "object": {"resharers": {"totalItems": 6, "selfLink": "https://www.googleapis.com/plus/v1/activities/z12ewbl4cwytex2sy22rx1mw5qjpebe34/people/resharers"}, "attachments": [{"fullImage": {"url": "https://lh4.googleusercontent.com/-MzhpwUsHet8/T-gjr_WMgFI/AAAAAAABlrg/S0EtAda1aVw/w288-h288/cratersky_perrot_1000.jpg", "width": 1000, "type": "image/jpeg", "height": 547}, "url": "https://plus.google.com/photos/115111485112027405250/albums/5757891361902401825/5757891362239053906", "image": {"url": "https://lh4.googleusercontent.com/-MzhpwUsHet8/T-gjr_WMgFI/AAAAAAABlrg/S0EtAda1aVw/w506-h750/cratersky_perrot_1000.jpg", "width": 506, "type": "image/jpeg", "height": 750}, "content": "cratersky_perrot_1000.jpg", "id": "115111485112027405250.5757891362239053906", "objectType": "photo"}], "url": "https://plus.google.com/115111485112027405250/posts/ErqpCjp3nQY", "actor": {"url": "https://plus.google.com/115111485112027405250", "image": {"url": "https://lh5.googleusercontent.com/-j7dVl48s1m8/AAAAAAAAAAI/AAAAAAAAAAA/CgbRNm9sWMM/photo.jpg?sz=50"}, "displayName": "Earth", "id": "115111485112027405250"}, "content": "<b><span class=\"proflinkWrapper\"><span class=\"proflinkPrefix\">+</span><a href=\"https://plus.google.com/112026139541760362193\" class=\"proflink\" oid=\"112026139541760362193\">Milky Way</a></span>\u00a0Over Piton de l&#39;Eau</b><br /><br />Sometimes, if you wait long enough for a clear and moonless night, the stars will come out with a vengeance. One such occasion occurred earlier this month at the Piton de l&#39;Eau on Reunion Island. In the foreground, surrounded by bushes and trees, lies a water filled volcanic crater serenely reflecting starlight. A careful inspection near the image center will locate Piton des Neiges, the highest peak on the island, situated several kilometers away. In the background, high above the lake, shines the light of hundreds of stars, most of which are within 100 light years, right in our stellar neighborhood. Far is the distance, arching majestically overhead, is the central band of our home Milky Way Galaxy, shining by the light of millions of stars each located typically thousands of light years away. The astrophotographer reports waiting for nearly two years for the sky and clouds to be just right to get the above shot.<br /><br />Image Credit &amp; Copyright: Luc Perrot<br />Explanation of the image from:\u00a0<a href=\"http://apod.nasa.gov/apod/ap120625.html\" class=\"ot-anchor\">http://apod.nasa.gov/apod/ap120625.html</a>", "plusoners": {"totalItems": 21, "selfLink": "https://www.googleapis.com/plus/v1/activities/z12ewbl4cwytex2sy22rx1mw5qjpebe34/people/plusoners"}, "replies": {"totalItems": 2, "selfLink": "https://www.googleapis.com/plus/v1/activities/z12ewbl4cwytex2sy22rx1mw5qjpebe34/comments"}, "id": "z13oxhmqtwufsbvmm23igrg5amzyvznu5", "objectType": "activity"}, "updated": "2012-06-25T15:22:48.992Z", "actor": {"url": "https://plus.google.com/106186407539128840569", "image": {"url": "https://lh4.googleusercontent.com/-JiDYXVr6Fd8/AAAAAAAAAAI/AAAAAAAAB7I/bHl2pymBVZQ/photo.jpg?sz=50"}, "displayName": "Daniel Harrington", "id": "106186407539128840569"}, "annotation": "<b>Water-Filled Crater and  <a class='ot-hashtag' href='https://plus.google.com/s/%23MilkyWay'>#MilkyWay</a> \u00a0- Great  <a class='ot-hashtag' href='https://plus.google.com/s/%23Photography'>#Photography</a> \u00a0- thanks for sharing!</b><br> <a class='ot-hashtag' href='https://plus.google.com/s/%23astrophotography'>#astrophotography</a> \u00a0 <a class='ot-hashtag' href='https://plus.google.com/s/%23landscapephotography'>#landscapephotography</a> \u00a0 <a class='ot-hashtag' href='https://plus.google.com/s/%23stars'>#stars</a> \u00a0 <a class='ot-hashtag' href='https://plus.google.com/s/%23naturephotography'>#naturephotography</a> \u00a0", "access": {"items": [{"type": "public"}], "kind": "plus#acl", "description": "Public"}, "verb": "share", "etag": "\"Mwea3qudNDf-hWWlPWi3n-YrU1Q/fNMVngcXQrVKCyPYlSqz4Mzbfng\"", "published": "2012-06-25T15:22:48.992Z", "id": "z12ewbl4cwytex2sy22rx1mw5qjpebe34"}, {"items": [{"inReplyTo": [{"url": "https://plus.google.com/106186407539128840569/posts/62u8QZhfG4U", "id": "z12ewbl4cwytex2sy22rx1mw5qjpebe34"}], "kind": "plus#comment", "plusoners": {"totalItems": 0}, "object": {"content": "wao!", "objectType": "comment"}, "updated": "2012-06-25T15:27:26.992Z", "actor": {"url": "https://plus.google.com/111897735460554846464", "image": {"url": "https://lh3.googleusercontent.com/-k3ywH6snTYA/AAAAAAAAAAI/AAAAAAAABC0/PBd251sAnEo/photo.jpg?sz=50"}, "displayName": "Jose Namias", "id": "111897735460554846464"}, "verb": "post", "etag": "\"Mwea3qudNDf-hWWlPWi3n-YrU1Q/5lOathfCjqyHxqPqClVfNPi0jbs\"", "published": "2012-06-25T15:27:26.992Z", "id": "z12ewbl4cwytex2sy22rx1mw5qjpebe34.1340638046992670", "selfLink": "https://www.googleapis.com/plus/v1/comments/z12ewbl4cwytex2sy22rx1mw5qjpebe34#1340638046992670"}, {"inReplyTo": [{"url": "https://plus.google.com/106186407539128840569/posts/62u8QZhfG4U", "id": "z12ewbl4cwytex2sy22rx1mw5qjpebe34"}], "kind": "plus#comment", "plusoners": {"totalItems": 0}, "object": {"content": "Magical...", "objectType": "comment"}, "updated": "2012-06-25T19:00:23.957Z", "actor": {"url": "https://plus.google.com/105196127831156341581", "image": {"url": "https://lh6.googleusercontent.com/-dUiGdPf4p50/AAAAAAAAAAI/AAAAAAAABQk/wg96yGRHxh0/photo.jpg?sz=50"}, "displayName": "Marilyn Jansen Lopes", "id": "105196127831156341581"}, "verb": "post", "etag": "\"Mwea3qudNDf-hWWlPWi3n-YrU1Q/4krxlZ0iFhU2CrUY4n2PeH8k2VQ\"", "published": "2012-06-25T19:00:23.957Z", "id": "z12ewbl4cwytex2sy22rx1mw5qjpebe34.1340650823957474", "selfLink": "https://www.googleapis.com/plus/v1/comments/z12ewbl4cwytex2sy22rx1mw5qjpebe34#1340650823957474"}], "kind": "plus#commentFeed", "etag": "\"Mwea3qudNDf-hWWlPWi3n-YrU1Q/22y1oZm9yxI6cKQqTxumi0uHD60\"", "title": "Google+ List of Comments for an Activity"}]