[{"kind": "plus#activity", "provider": {"title": "Google+"}, "title": "If you start a high-risk business, it meant you invite the risk component for your business. To ignore...", "url": "https://plus.google.com/114559372279829652289/posts/WUnMSF9S6yV", "object": {"resharers": {"totalItems": 0, "selfLink": "https://www.googleapis.com/plus/v1/activities/z13og3cxaxqfddbxk04cfbkzznqpefazoh0/people/resharers"}, "attachments": [{"fullImage": {"url": "https://lh5.googleusercontent.com/-duuYvmMmn2A/UhyGD29oB9I/AAAAAAAAARg/slfT3V5hl9Q/PRPRPRPRPR.jpg", "width": 2048, "type": "image/jpeg", "height": 1536}, "url": "https://plus.google.com/photos/114559372279829652289/albums/5916751407563181153/5916751411309709266?authkey=CK6v6rj9mrnBQg", "image": {"url": "https://lh5.googleusercontent.com/-duuYvmMmn2A/UhyGD29oB9I/AAAAAAAAARg/slfT3V5hl9Q/w506-h750/PRPRPRPRPR.jpg", "width": 506, "type": "image/jpeg", "height": 750}, "content": "", "id": "114559372279829652289.5916751411309709266", "objectType": "photo"}], "url": "https://plus.google.com/114559372279829652289/posts/WUnMSF9S6yV", "content": "If you start a high-risk business, it meant you invite the risk component for your business. To ignore this problem, you need to provide a high-risk merchant account or credit card. In the USA, High Risk Credit Card Merchant Account offers a trustful service for credit card processing.<br />For details, visit this link...<br /><a href=\"http://goo.gl/P3TyFd\" class=\"ot-anchor\" rel=\"nofollow\">http://goo.gl/P3TyFd</a>", "plusoners": {"totalItems": 0, "selfLink": "https://www.googleapis.com/plus/v1/activities/z13og3cxaxqfddbxk04cfbkzznqpefazoh0/people/plusoners"}, "replies": {"totalItems": 0, "selfLink": "https://www.googleapis.com/plus/v1/activities/z13og3cxaxqfddbxk04cfbkzznqpefazoh0/comments"}, "objectType": "note"}, "updated": "2013-08-27T11:18:21.212Z", "actor": {"url": "https://plus.google.com/114559372279829652289", "image": {"url": "https://lh5.googleusercontent.com/-2LN6VRba03w/AAAAAAAAAAI/AAAAAAAAAJ4/67L-Ik_GTuU/photo.jpg?sz=50"}, "displayName": "Don Johnson", "id": "114559372279829652289"}, "access": {"items": [{"type": "public"}], "kind": "plus#acl", "description": "Public"}, "verb": "post", "etag": "\"Mwea3qudNDf-hWWlPWi3n-YrU1Q/B_mAfoUTw2YNOdmvPsXKr6DLGzg\"", "published": "2013-08-27T11:18:21.212Z", "id": "z13og3cxaxqfddbxk04cfbkzznqpefazoh0"}, "NONE"]