[{"kind": "plus#activity", "provider": {"title": "Reshared Post"}, "title": "Challenge: 30 Days of One Direction\nDay 3: Who's your favorite boy and why?\nThis is actually really ...", "url": "https://plus.google.com/108051008630424272755/posts/Pmj7qxJcsaC", "object": {"resharers": {"totalItems": 0, "selfLink": "https://www.googleapis.com/plus/v1/activities/z13uyl5gnpvlj34gc04cdbfrgnvnsrkwev40k/people/resharers"}, "attachments": [{"fullImage": {"url": "https://lh5.googleusercontent.com/-4Qrp8wjBoK0/ULtpniAn4rI/AAAAAAAAEjo/hQKV5yQdrcM/w288-h288/tumblr_m9a614z5zr1qf9hn4.gif", "width": 500, "type": "image/jpeg", "height": 280}, "url": "https://plus.google.com/photos/109154044673672471593/albums/5817359466035044897/5817359471544361650", "image": {"url": "https://lh5.googleusercontent.com/-4Qrp8wjBoK0/ULtpniAn4rI/AAAAAAAAEjo/hQKV5yQdrcM/w506-h750/tumblr_m9a614z5zr1qf9hn4.gif", "width": 506, "type": "image/jpeg", "height": 750}, "content": "tumblr_m9a614z5zr1qf9hn4.gif", "id": "109154044673672471593.5817359471544361650", "objectType": "photo"}], "url": "https://plus.google.com/109154044673672471593/posts/ToM6zRvCQuy", "actor": {"url": "https://plus.google.com/109154044673672471593", "image": {"url": "https://lh4.googleusercontent.com/-7C6j-VqcxsA/AAAAAAAAAAI/AAAAAAAAJLs/zf2D-sWtefA/photo.jpg?sz=50"}, "displayName": "One Direction Infection Fan Page", "id": "109154044673672471593"}, "content": "<b>Challenge: 30 Days of One Direction</b><br /><i>Day 3: Who&#39;s your favorite boy and why?</i><br />This is actually really hard....I like all of them for different reasons.<br /><b><i>Louis:</i></b> He is really funny and he would be someone I would want to cheer me up when I&#39;m down.<br /><b><i>Liam:</i></b> He is very protective and if I was ever friends (or more) with him I would feel safe around him.<br /><b><i>Niall:</i></b> He is so carefree and likes scary movies (which I love)!<br /><b><i>Harry:</i></b> He is really nice and seems like he would be trustful and honest.<br /><b><i>Zayn:</i></b> He has a really good sense in style and I know I could go to him for any style-related thing. \u00a0He also seem very nice.", "plusoners": {"totalItems": 0, "selfLink": "https://www.googleapis.com/plus/v1/activities/z13uyl5gnpvlj34gc04cdbfrgnvnsrkwev40k/people/plusoners"}, "replies": {"totalItems": 0, "selfLink": "https://www.googleapis.com/plus/v1/activities/z13uyl5gnpvlj34gc04cdbfrgnvnsrkwev40k/comments"}, "id": "z122etlxwvz5ulb5004ccz5jnlbtjzyimag", "objectType": "activity"}, "updated": "2013-03-06T16:18:08.732Z", "actor": {"url": "https://plus.google.com/108051008630424272755", "image": {"url": "https://lh5.googleusercontent.com/-jyYYAL2BoNY/AAAAAAAAAAI/AAAAAAAAId0/AsX5C1xhcSE/photo.jpg?sz=50"}, "displayName": "Paige Frank", "id": "108051008630424272755"}, "access": {"items": [{"type": "public"}], "kind": "plus#acl", "description": "Public"}, "verb": "share", "etag": "\"Mwea3qudNDf-hWWlPWi3n-YrU1Q/gq1R_xSqKYoduqZDyERvtt8Ijkg\"", "published": "2013-03-06T16:18:08.732Z", "id": "z13uyl5gnpvlj34gc04cdbfrgnvnsrkwev40k"}, "NONE"]