[{"kind": "plus#activity", "provider": {"title": "Google+"}, "title": "May the beauty\nof Diwali season\nFill your home with Happiness,\nAnd may the coming year\nProvide you with...", "url": "https://plus.google.com/105055828920137973295/posts/5Su1QsK54fS", "object": {"resharers": {"totalItems": 0, "selfLink": "https://www.googleapis.com/plus/v1/activities/z13kvfhjyqnqhvmku23ez5cawzj1d5cmh/people/resharers"}, "attachments": [{"displayName": "May the beauty\nof Diwali season\nFill your home with Happiness,\nAnd may the coming year\nProvide you with all\nthat bring you happiness!!!\nMay the divine light of Diwali\nspread into your Life\nserenity, prosperity, bliss\nand good health.\nHappy Diwali Friends... :-) :-)", "fullImage": {"url": "https://lh6.googleusercontent.com/-KHQJgPBK7Yo/UnOFrE5euyI/AAAAAAAAApw/q1sbFiOQN9U/w276-h182/diwali.jpg", "width": 276, "type": "image/jpeg", "height": 182}, "url": "https://plus.google.com/photos/105055828920137973295/albums/5941239305704348049/5941239308527516450", "image": {"url": "https://lh6.googleusercontent.com/-KHQJgPBK7Yo/UnOFrE5euyI/AAAAAAAAApw/q1sbFiOQN9U/w506-h750/diwali.jpg", "width": 506, "type": "image/jpeg", "height": 750}, "content": "diwali.jpg", "id": "105055828920137973295.5941239308527516450", "objectType": "photo"}], "url": "https://plus.google.com/105055828920137973295/posts/5Su1QsK54fS", "content": "May the beauty<br />of Diwali season<br />Fill your home with Happiness,<br />And may the coming year<br />Provide you with all<br />that bring you happiness!!!<br />May the divine light of Diwali<br />spread into your Life<br />serenity, prosperity, bliss<br />and good health.\u00a0<br />Happy Diwali Friends... :-) :-)", "plusoners": {"totalItems": 3, "selfLink": "https://www.googleapis.com/plus/v1/activities/z13kvfhjyqnqhvmku23ez5cawzj1d5cmh/people/plusoners"}, "replies": {"totalItems": 0, "selfLink": "https://www.googleapis.com/plus/v1/activities/z13kvfhjyqnqhvmku23ez5cawzj1d5cmh/comments"}, "objectType": "note"}, "updated": "2013-11-01T10:48:20.199Z", "actor": {"url": "https://plus.google.com/105055828920137973295", "image": {"url": "https://lh6.googleusercontent.com/-5yBxYp1Gn_M/AAAAAAAAAAI/AAAAAAAAAJw/bUN2-Irsq4U/photo.jpg?sz=50"}, "displayName": "Tejaswini Rathi", "id": "105055828920137973295"}, "access": {"items": [{"type": "public"}], "kind": "plus#acl", "description": "Public"}, "verb": "post", "etag": "\"Mwea3qudNDf-hWWlPWi3n-YrU1Q/Cq46xB80cYaGJl6Js6ZNT0GMk28\"", "published": "2013-11-01T10:48:20.199Z", "id": "z13kvfhjyqnqhvmku23ez5cawzj1d5cmh"}, "NONE"]